{
    "by_freq": {
        "52 weeks 1 days": 27,
        "25 weeks 6 days": 1,
        "13 weeks 1 days": 2,
        "8 weeks 5 days": 1,
        "4 weeks 2 days": 183,
        "2 weeks 3 days": 1,
        "2 weeks 1 days": 2,
        "2 weeks": 10,
        "1 weeks 3 days": 1,
        "1 weeks": 1764,
        "6 days": 1,
        "5 days": 2,
        "4 days": 9,
        "3 days": 34,
        "2 days": 32,
        "1 days": 2579,
        "23 hours": 1,
        "21 hours": 1,
        "18 hours": 18,
        "17 hours": 3,
        "16 hours": 28,
        "15 hours": 10,
        "14 hours": 34,
        "13 hours": 28,
        "12 hours": 370,
        "11 hours": 43,
        "10 hours": 33,
        "9 hours": 43,
        "8 hours": 72,
        "7 hours": 43,
        "6 hours": 225,
        "5 hours": 54,
        "4 hours": 295,
        "3 hours": 188,
        "2 hours": 329,
        "1 hours": 404,
        "30 minutes": 64,
        "29 minutes": 14,
        "20 minutes": 10,
        "17 minutes": 1,
        "15 minutes": 23,
        "10 minutes": 25,
        "9 minutes": 1,
        "7 minutes": 1,
        "6 minutes": 14,
        "5 minutes": 90,
        "2 minutes": 1,
        "1 minutes": 560,
        "": 12
    },
    "by_count": {
        "1 days": 2579,
        "1 weeks": 1764,
        "1 minutes": 560,
        "1 hours": 404,
        "12 hours": 370,
        "2 hours": 329,
        "4 hours": 295,
        "6 hours": 225,
        "3 hours": 188,
        "4 weeks 2 days": 183,
        "5 minutes": 90,
        "8 hours": 72,
        "30 minutes": 64,
        "5 hours": 54,
        "11 hours": 43,
        "9 hours": 43,
        "7 hours": 43,
        "3 days": 34,
        "14 hours": 34,
        "10 hours": 33,
        "2 days": 32,
        "16 hours": 28,
        "13 hours": 28,
        "52 weeks 1 days": 27,
        "10 minutes": 25,
        "15 minutes": 23,
        "18 hours": 18,
        "6 minutes": 14,
        "29 minutes": 14,
        "": 12,
        "2 weeks": 10,
        "15 hours": 10,
        "20 minutes": 10,
        "4 days": 9,
        "17 hours": 3,
        "2 weeks 1 days": 2,
        "13 weeks 1 days": 2,
        "5 days": 2,
        "7 minutes": 1,
        "8 weeks 5 days": 1,
        "2 weeks 3 days": 1,
        "25 weeks 6 days": 1,
        "23 hours": 1,
        "21 hours": 1,
        "2 minutes": 1,
        "1 weeks 3 days": 1,
        "6 days": 1,
        "9 minutes": 1,
        "17 minutes": 1
    }
}